---
layout: post
title: "Java基础"
date: 2018-01-01 00:00:00
description: "Java基础"
categories:
- java
permalink: java
---

### 目录
* [1. String](#1-String)

#### 1. String  
##### 1.1 重载 “+” 与 StringBuilder  
```vim
public class T {
    public static void main(String[] args) {
       String a = "-";
       String b = "123" + a + "456" + a + 789;
       System.out.println(b);
    }
}

// 使用JDK自带javap命令生成字节码 javap -c T.class 

public class T {
  public T();
    Code:
       0: aload_0
       1: invokespecial #1                  // Method java/lang/Object."<init>":()V
       4: return

  public static void main(java.lang.String[]);
    Code:
       0: ldc           #2                  // String -
       2: astore_1
       3: new           #3                  // class java/lang/StringBuilder -- 编译器自动引用java.lang.StringBuilder类, 并实例化了一个StringBuilder对象
       6: dup
       7: invokespecial #4                  // Method java/lang/StringBuilder."<init>":()V
      10: ldc           #5                  // String 123 -- 每个运算符 "+" 调用一次 append 方法
      12: invokevirtual #6                  // Method java/lang/StringBuilder.append:(Ljava/lang/String;)Ljava/lang/StringBuilder;
      15: aload_1
      16: invokevirtual #6                  // Method java/lang/StringBuilder.append:(Ljava/lang/String;)Ljava/lang/StringBuilder;
      19: ldc           #7                  // String 456
      21: invokevirtual #6                  // Method java/lang/StringBuilder.append:(Ljava/lang/String;)Ljava/lang/StringBuilder;
      24: aload_1
      25: invokevirtual #6                  // Method java/lang/StringBuilder.append:(Ljava/lang/String;)Ljava/lang/StringBuilder;
      28: sipush        789
      31: invokevirtual #8                  // Method java/lang/StringBuilder.append:(I)Ljava/lang/StringBuilder;
      34: invokevirtual #9                  // Method java/lang/StringBuilder.toString:()Ljava/lang/String; -- 最后调用 toString 方法, 返回String
      37: astore_2
      38: getstatic     #10                 // Field java/lang/System.out:Ljava/io/PrintStream;
      41: aload_2
      42: invokevirtual #11                 // Method java/io/PrintStream.println:(Ljava/lang/String;)V
      45: return
}

// 再看看循环使用运算符 "+"  

public class T {
    public static void main(String[] args) {
       String a = "";
       for(int i=0; i<10; i++) {
          a += i;
       }
       System.out.println(a);
    }
}

public class T {
  public T();
    Code:
       0: aload_0
       1: invokespecial #1                  // Method java/lang/Object."<init>":()V
       4: return

  public static void main(java.lang.String[]);
    Code:
       0: ldc           #2                  // String
       2: astore_1
       3: iconst_0
       4: istore_2
       5: iload_2 -- 循环开始..
       6: bipush        10
       8: if_icmpge     36
      11: new           #3                  // class java/lang/StringBuilder -- 每次循环都会实例化一个StringBuilder对象
      14: dup
      15: invokespecial #4                  // Method java/lang/StringBuilder."<init>":()V
      18: aload_1
      19: invokevirtual #5                  // Method java/lang/StringBuilder.append:(Ljava/lang/String;)Ljava/lang/StringBuilder;
      22: iload_2
      23: invokevirtual #6                  // Method java/lang/StringBuilder.append:(I)Ljava/lang/StringBuilder;
      26: invokevirtual #7                  // Method java/lang/StringBuilder.toString:()Ljava/lang/String;
      29: astore_1
      30: iinc          2, 1
      33: goto          5  -- 跳转到第5行..
      36: getstatic     #8                  // Field java/lang/System.out:Ljava/io/PrintStream;
      39: aload_1
      40: invokevirtual #9                  // Method java/io/PrintStream.println:(Ljava/lang/String;)V
      43: return
}
```
